Workbook

Sheet Dashboard
C2: ENERGY FUTURES BID / ASK SPREAD MONITOR
B4: TT MARKET | C4: CME
B5: TT SHORT NAME | C5: INSTRUMENT ID
B6: RBV6 | F6: Symbol | G6: Contract | H6: Bid | I6: Ask | J6: Gap | K6: High | L6: Low | N6: Symbol | O6: Contract | P6: Bid | Q6: Ask | R6: Gap | S6: High | T6: Low
B7: HOV6 | F7: HOV26 HO Oct 26 | G7: HO Oct 26 | N7: BZV26 BZ Oct 26 | O7: BZ Oct 26
B8: BZV6 | F8: CLV26 CL Oct 26 | G8: CL Oct 26 | N8: CLV26 CL Oct 26 | O8: CL Oct 26
B9: CLV6 | F9: HO | CL Oct 26 Crack | N9: BZ - CL
B10: CL Oct26 - BZ Oct26 Inter-Product
F11: Symbol | G11: Contract | H11: Bid | I11: Ask | J11: Gap | K11: High | L11: Low | N11: Symbol | O11: Contract | P11: Bid | Q11: Ask | R11: Gap | S11: High | T11: Low
B12: Oct26 HO-CL Crack | F12: RBV26 | G12: RB Oct 26 | N12: CL Oct-Dec Calendar
F13: HOV26 | G13: HO Oct 26
F14: CLV26 | G14: CL Oct 26
F15: 3:2:1
F17: Z-SCORE MONITOR z is for ENTRIES only - exits act on money, never on z. The chime fires on the CROSSING of ENTRY_Z, once.
F18: Spread | H18: Bid | I18: Direction | J18: Z-score | K18: Mean | L18: Std Dev | N18: Signal | P18: Window | Q18: Costs $ | R18: Win $ | S18: TAKE PROFIT | T18: TP in sigma
F19: HO | CL Crack
F20: BZ - CL
F21: 3:2:1
F22: CL Oct-Dec Calendar
F24: STOPPED | H24: - | N24: > START | P24: # STOP | R24: TEST CHIME

Sheet Detail
B1: DETAIL - full breakdown behind the Dashboard
B2: Same engine, same numbers. The Dashboard shows the three spreads you trade from; this sheet shows everything that stands behind them, for all four slots.
B4: OUTRIGHT LEGS
B5: Symbol | C5: Instrument ID | D5: Description | E5: Contract | H5: Bid | I5: Ask | J5: High | K5: Low | L5: Mid | M5: Gap
B6: RBV6 | D6: RBOB Gasoline Oct26 | E6: 42,000 gal
B7: HOV6 | D7: NY Harbor ULSD Oct26 | E7: 42,000 gal
B8: CLV6 | D8: WTI Crude Oct26 | E8: 1,000 bbl
B9: BZV6 | D9: Brent Last Day Fin Oct26 | E9: 1,000 bbl
B11: DERIVED & LISTED SPREADS
B12: Spread | C12: Basis | D12: Crossing convention | H12: Bid | I12: Ask | L12: Mid | M12: Gap
B13: BZ - CL | C13: legged | D13: bid = BZ bid - CL ask ; ask = BZ ask - CL bid
B14: HO/CL crack | C14: legged | D14: bid = HO bid x42 - CL ask ; ask = HO ask x42 - CL bid
B15: 3:2:1 crack | C15: legged | D15: bid sells products at the bid and buys crude at the ask; ask mirrors it
B16: CL Oct26 - BZ Oct26 Inter-Product | C16: listed | D16: exchange-listed - one quote, no leg risk
B17: Oct26 HO-CL Crack | C17: listed | D17: exchange-listed - one quote, no leg risk
B19: PER-SPREAD BREAKDOWN
B20: Metric | C20: Unit / note | D20: SPREAD 1 | E20: SPREAD 2 | F20: SPREAD 3 | G20: SPREAD 4
B21: Spread
B22: Definition | C22: LegB - beta x LegA
B23: Mode
B24: HEDGE_RATIO (beta) | C24: stamped pair ->
B25: USD per 1.00 of spread | C25: per lot
B26: MARKET (touch, shown separately from the statistic)
B27: Spread bid
B28: Spread ask
B29: Spread mid <- feeds the statistic
B30: Bid-Ask Gap | C30: spread units
B31: WINDOW
B32: Stored samples in window | C32: after dedupe + store gate
B33: Window elapsed | C33: min
B34: Warm-up gate | C34: binding gate
B35: Feed rate | C35: quote CHANGES / min
B36: Feed status
B37: STATISTICS (FROZEN - republished every STATS_REFRESH_MIN)
B38: Mean (frozen)
B39: Std Dev (frozen)
B40: Std Dev in dollars | C40: sigma x USD/pt x LOTS
B41: Stats age / next refresh | C41: min
B42: Z (live, vs frozen mean & sigma)
B43: SIGNAL
B44: COST OF THE ROUND TRIP
B45: Direction
B46: Entry reference (touch)
B47: Commission | C47: contracts x rate x LOTS
B48: Crossing cost - LEGGING
B49: Crossing cost - LISTED
B50: TOTAL COST (this mode)
B51: TAKE PROFIT (exits act on MONEY, never on z)
B52: TP rule in force
B53: Notional (per NOTIONAL_BASIS)
B54: Win target (WIN_PCT x notional)
B55: Costs in spread units
B56: Win in spread units
B57: Break-even spread | C57: absolute level
B58: TAKE-PROFIT spread | C58: absolute level
B59: TP distance | C59: spread units
B60: TP in sigma | C60: x sigma
B61: Target z | C61: z at the TP level
B62: TP beyond the mean?
B63: EDGE FILTER (a separate gate from ENTRY_Z)
B64: Expected capture | C64: 0.5 x |z| x sigma x USD/pt x LOTS
B65: Required | C65: EDGE_MULTIPLE x total cost
B66: EDGE VERDICT
B67: Min sigma to pass at live z | C67: spread units
B69: The EDGE FILTER is a different gate from ENTRY_Z. ENTRY_Z decides when the chime fires; the edge filter asks whether the expected capture clears the round trip by EDGE_MULTIPLE. A highlighted z that fails the edge filter is still not a trade worth taking.
B70: ALERT_ONLY_IF_EDGE_PASSES on Config decides whether a failing edge filter also silences the chime. It ships FALSE, so the chime follows ENTRY_Z alone.

Sheet Config
A1: CONFIG - every parameter in its own labelled cell
A2: LEGEND: yellow / blue = EDIT THESE. black = formula, do not edit. A changed value takes effect on the NEXT TIMER TICK - no restart, no VBA edit.
A3: Exception: LOOKBACK_MIN redefines the window, so stored history is re-evaluated against the new width on the next stats refresh and the warm-up gates re-apply.
A4: VBA finds a parameter by matching column A exactly, so you may insert or reorder rows freely - but never rename a parameter in column A.
A5: FOUR DECOUPLED RATES: CAPTURE_MS (poll for a changed quote) > STORE_MIN_INTERVAL_MS (what reaches the window) > PRICE_REFRESH_MS (what repaints) > STATS_REFRESH_MIN (when mean and sigma are republished). Capturing fast buys alert latency, not a better sigma.
A7: ENGINE / SAMPLING
A8: Parameter | B8: Value | C8: Default | D8: Units | E8: Meaning
A9: CAPTURE_MS | B9: 100 | C9: 100 | D9: ms | E9: RATE 1 of 4. How often the feed is POLLED for a changed quote. Drives latency to the chime, NOT sigma - after dedupe the window holds quote changes, not poll ticks. Sub-second needs the user32 timer; at 1000+ the module falls back to Application.OnTime.
A10: STORE_MIN_INTERVAL_MS | B10: 0 | C10: 0 | D10: ms | E10: RATE 2 of 4. Minimum spacing between STORED samples. 0 = full fidelity. Leave it at 0 for the first week or two to characterise the microstructure, then set 250-1000: subsampling a mean-reverting level series is unbiased, so it is 3-10x less memory for the same mean and sigma.
A11: PRICE_REFRESH_MS | B11: 500 | C11: 500 | D11: ms | E11: RATE 3 of 4. How often the display may repaint. Independent of capture and of storage - a number showing more digits than the market moves in will appear to change constantly.
A12: CONFIG_REFRESH_MS | B12: 1000 | C12: 1000 | D12: ms | E12: How often this sheet is re-read. A value changed here takes effect within this long - no restart, no VBA edit.
A13: RTD_THROTTLE_MS | B13: 100 | C13: 100 | D13: ms | E13: Application.RTD.ThrottleInterval set on start. Match it to CAPTURE_MS. Excel's default is 2000.
A14: WATCHDOG_SEC | B14: 5 | C14: 5 | D14: s | E14: Application.OnTime watchdog. Re-arms the high-resolution timer if Excel killed it (a modal dialog will) and picks up a changed CAPTURE_MS.
A15: STALE_SEC | B15: 15 | C15: 15 | D15: s | E15: No new quote id for this long => feed marked STALE and alerts go silent.
A16: FLUSH_SEC | B16: 60 | C16: 60 | D16: s | E16: How often the recovery snapshot is written to the hidden Buffer sheet.
A17: FLUSH_DECIMATE_MS | B17: 1000 | C17: 1000 | D17: ms | E17: The recovery snapshot is decimated to this spacing. Unbiased for mean and sigma, and it keeps a 120-minute window near 7,200 rows instead of tens of thousands.
A18: BUFFER_CAPACITY | B18: 80000 | C18: 80000 | D18: samples | E18: Circular-buffer capacity per spread. 4 spreads x 80,000 x 16 bytes is about 5 MB of VBA array, held in memory, not in cells.
A19: TICK_ARCHIVE_ENABLED | B19: TRUE | C19: TRUE | D19: bool | E19: Write every CHANGED quote to a CSV on disk. This is the one chance to characterise the spread's microstructure and to verify that coarser storage loses nothing real. Turn it off once STORE_MIN_INTERVAL_MS is set.
A20: TICK_ARCHIVE_PATH | D20: folder | E20: Folder for the tick CSVs. Blank = a 'ticks' folder beside the workbook. One file per spread per day.
A21: TICK_ARCHIVE_BATCH | B21: 500 | C21: 500 | D21: lines | E21: Lines buffered in memory before a file write, so archiving never stalls the capture timer.
A23: WINDOW / STATISTICS
A24: Parameter | B24: Value | C24: Default | D24: Units | E24: Meaning
A25: LOOKBACK_MIN | B25: 120 | C25: 120 | D25: min | E25: Rolling window width (90 or 120). Changing it re-evaluates stored history on the next stats refresh and re-applies the warm-up gates.
A26: STATS_REFRESH_MIN | B26: 5 | C26: 5 | D26: min | E26: How often mean/sigma are recomputed and re-published. Held FROZEN in between; live z is measured against the frozen values.
A27: MIN_SAMPLES | B27: 300 | C27: 300 | D27: quotes | E27: Warm-up gate 1. Quotes needed before any z is shown.
A28: MIN_HISTORY_MIN | B28: 120 | C28: 120 | D28: min | E28: Warm-up gate 2. Window span needed before any z is shown. BOTH gates must pass. MUST BE LESS THAN LOOKBACK_MIN: eviction drops samples older than the lookback, so the span approaches it but never reaches it, and a value at or above LOOKBACK_MIN would never be satisfied. Anything above 98% of LOOKBACK_MIN is clamped to that, and the clamp is noted once in the Log.
A29: MIN_SIGMA | B29: 0 | C29: 0 | D29: spread | E29: Sigma floor. Below this the window is degenerate and NO z is shown. Set once sigma has actually been measured.
A30: MAX_ABS_Z | B30: 25 | C30: 25 | D30: z | E30: Absurd-z guard. Above this, show 'no usable z' rather than a number.
A32: SIGNAL THRESHOLDS
A33: Parameter | B33: Value | C33: Default | D33: Units | E33: Meaning
A34: ENTRY_Z | B34: 2.5 | C34: 2.5 | D34: z | E34: Highlight and chime at or above this |z|. 2.0 and 2.5 are both reasonable; 2.0 fires more often and needs a larger sigma to stay worth trading.
A35: MAX_ENTRY_Z | B35: 4.5 | C35: 4.5 | D35: z | E35: Entry CEILING. At or above this, do NOT highlight - that is a momentum spike, not a reversion setup. Keep the band at least 1 sigma wide.
A36: THIN_FEED_QPM | B36: 6 | C36: 6 | D36: q/min | E36: Feed rate at or below which the quotes/min display turns amber.
A37: SPREAD_QUOTE_CONVENTION | B37: CROSSING | C37: CROSSING | D37: text | E37: How the spread rows on Dashboard quote Bid and Ask. CROSSING: sell LegB at the bid and buy LegA at the ask, mirrored for the ask - the Gap is then the true cost of crossing and is always positive. SAME_SIDE: bid-minus-bid and ask-minus-ask, as the original sheet's rows 9 computed. Under SAME_SIDE the Gap is a DIFFERENCE of gaps, which understates the crossing cost and can go negative.
A39: SIZING / COSTS
A40: Parameter | B40: Value | C40: Default | D40: Units | E40: Meaning
A41: LOTS | B41: 1 | C41: 1 | D41: lots | E41: Contracts per leg, for the cost and take-profit maths.
A42: TP_MODE | B42: PCT_NOTIONAL | C42: PCT_NOTIONAL | D42: text | E42: PCT_NOTIONAL: Take Profit = Entry + Costs + (WIN_PCT x Notional). TARGET_USD: the older rule, Take Profit = Entry + Costs + TARGET_NET_USD.
A43: WIN_PCT | B43: 0.01 | C43: 0.01 | D43: fraction | E43: Percentage win, as a FRACTION - 0.01 is 1%, 0.02 is 2%. Used only when TP_MODE = PCT_NOTIONAL.
A44: NOTIONAL_BASIS | B44: SPREAD_VALUE | C44: SPREAD_VALUE | D44: text | E44: What WIN_PCT is taken OF. SPREAD_VALUE = |spread| x USD/pt x LOTS. ONE_LEG = the crude leg's full contract value. BOTH_LEGS = both legs' contract value added. These differ by roughly 10x - read the note below the table before changing it.
A45: TP_ENTRY_BASIS | B45: BID | C45: BID | D45: text | E45: Which price the take-profit is measured from. BID: always the bid, the price you sell at - exact for a High-to-Low trade, optimistic by the spread's own gap on a Low-to-High one. TOUCH: prices each direction at the side it really trades on (bid when selling, ask when buying).
A46: TARGET_NET_USD | B46: 150 | C46: 150 | D46: USD | E46: Desired profit AFTER all costs. Used only when TP_MODE = TARGET_USD.
A47: EDGE_MULTIPLE | B47: 1.5 | C47: 1.5 | D47: x | E47: Expected capture must clear the round trip by this multiple.
A48: RATE_ORIENT_PER_SIDE | B48: 0.35 | C48: 0.35 | D48: USD | E48: Orient clearing + execution, per contract per side. Source: Orient rate card 2026-08-21, Ver.26.8.17.
A49: RATE_FIX_PER_SIDE | B49: 0.06 | C49: 0.06 | D49: USD | E49: FIX / platform transaction fee, per contract per side. Same rate card.
A50: RATE_CME_PER_SIDE | B50: 1.5 | C50: 1.5 | D50: USD | E50: CME exchange + clearing, per contract per side. Same rate card.
A52: AUDIBLE ALERT
A53: Parameter | B53: Value | C53: Default | D53: Units | E53: Meaning
A54: ALERT_ENABLED | B54: TRUE | C54: TRUE | D54: bool | E54: MASTER MUTE. FALSE silences every sound.
A55: ALERT_SOUND_PATH | B55: C:\Windows\Media\chimes.wav | C55: C:\Windows\Media\chimes.wav | D55: path | E55: Single short 'ting' played on an entry-band crossing.
A56: ALERT_SOUND_PATH_CEILING | B56: C:\Windows\Media\notify.wav | C56: C:\Windows\Media\notify.wav | D56: path | E56: Distinct tone for crossing MAX_ENTRY_Z. That is 'stand down', not 'get in'.
A57: ALERT_REARM_MARGIN | B57: 0.25 | C57: 0.25 | D57: z | E57: Hysteresis. Do not re-arm until |z| falls back below ENTRY_Z - this margin.
A58: ALERT_COOLDOWN_SEC | B58: 60 | C58: 60 | D58: s | E58: Minimum seconds between alerts for the same spread.
A59: ALERT_ONLY_IF_EDGE_PASSES | B59: FALSE | C59: FALSE | D59: bool | E59: FALSE = the chime follows ENTRY_Z alone. TRUE = also stay silent when the edge filter fails, on the argument that a sound for a trade you should not take trains you to ignore the sound. Ships FALSE by request; the edge verdict is still shown on Detail.
A60: ALERT_SPEAK | B60: FALSE | C60: FALSE | D60: bool | E60: TRUE also speaks the spread name (Application.Speech). Useful when watching four at once.
A62: PERSISTENCE / LOGGING
A63: Parameter | B63: Value | C63: Default | D63: Units | E63: Meaning
A64: WARM_START_ENABLED | B64: TRUE | C64: TRUE | D64: bool | E64: On open, reload the flushed buffer so a restart does not cost another two hours of warm-up.
A65: WARM_START_MAX_AGE_MIN | B65: 180 | C65: 180 | D65: min | E65: Only reload if the newest saved sample is younger than this.
A66: LOG_ENABLED | B66: TRUE | C66: TRUE | D66: bool | E66: Write signal events to the Log sheet.
A67: LOG_MAX_ROWS | B67: 20000 | C67: 20000 | D67: rows | E67: Log is trimmed to this many rows.
A69: DERIVED COMMISSION (formulas - do not edit)
A70: Parameter | B70: Value | C70: Default | D70: Units | E70: Meaning
A71: COMMISSION_CONSERVATIVE | B71: =2*(B48+B49+B50) | E71: Per lot PER LEG, round turn, reading CME's 1.50 as per SIDE. This is the conservative reading and the one to use.
A72: COMMISSION_IF_CME_PER_RT | B72: =2*(B48+B49)+B50 | E72: The same figure if CME's 1.50 turns out to be per ROUND TURN rather than per side.
A73: COMMISSION_BASIS | B73: CONSERVATIVE | C73: CONSERVATIVE | E73: CONSERVATIVE or CME_PER_RT. An understated cost model approves losing trades invisibly; an overstated one only refuses trades, visibly. Leave it on CONSERVATIVE.
A74: COMMISSION_PER_LOT_ROUND_TURN | B74: =IF(B73="CME_PER_RT",B72,B71) | E74: USD per lot per leg, round turn. This is what the cost model actually uses.
A76: INSTRUMENTS - CONTRACT ROLL
A77: These six cells are the ONLY place a TT short name appears. Every RTD call on the hidden Feed sheet reads them, and the Dashboard's own symbol column is written back from them, so the two can never disagree.
A78: CME month codes: F Jan G Feb H Mar J Apr K May M Jun N Jul Q Aug U Sep V Oct X Nov Z Dec
A79: Roll every leg of a spread together. A November Brent against an October WTI is a different instrument from the one whose mean and sigma you measured, and the window should be cleared when you change one.
A80: CL is a leg of ALL THREE spreads. Moving it to November while RBOB and ULSD stay in October turns the cracks into a crack PLUS a calendar spread - not the thing the z-score was measuring. Roll RBOB and ULSD with it.
A81: Slot | B81: TT short name | C81: Instrument | E81: Used as
A82: INSTRUMENT_1 | B82: RBV6 | C82: RBOB Gasoline | E82: leg of the 3:2:1
A83: INSTRUMENT_2 | B83: HOV6 | C83: NY Harbor ULSD | E83: leg of HO/CL and the 3:2:1
A84: INSTRUMENT_3 | B84: CLX6 | C84: WTI Crude | E84: leg of every spread
A85: INSTRUMENT_4 | B85: BZX6 | C85: Brent Last Day Financial | E85: leg B of BZ - CL
A86: INSTRUMENT_5 | B86: CL Nov26 - BZ Nov26 Inter-Product | C86: Exchange-listed inter-product | E86: listed comparison
A87: INSTRUMENT_6 | B87: Nov26 HO-CL Crack | C87: Exchange-listed crack | E87: listed comparison
A88: INSTRUMENT_7 | B88: CL Oct26-Dec26 Calendar | C88: Exchange-listed calendar | E88: slot 4 - monitored
A91: SPREAD_TABLE_START - up to 4 monitored spreads, one buffer each
A92: Leg COMPOSITION (which instruments, and their weights) is defined by the labelled formulas in the MONITOR LEGS block on the hidden Feed sheet. Everything below is hot-reloaded each tick.
A93: Slot | B93: Enabled | C93: Display name | D93: Mode | E93: HEDGE_RATIO (beta) | F93: Beta stamped for pair | G93: USD per 1.00 of spread, per lot | H93: Contracts charged commission | I93: Tick size | J93: Decimals | K93: Listed equivalent (cost comparison)
A94: SPREAD_1 | B94: TRUE | C94: BZ - CL (Brent LDF - WTI) | D94: LEGGED | E94: 1 | F94: BZV6 / CLV6, derived 2026-08 (RELATED pair - no fair value, empirical mean only) | G94: 1000 | H94: 2 | I94: 0.01 | J94: 2 | K94: CL Oct26 - BZ Oct26 Inter-Product
A95: SPREAD_2 | B95: TRUE | C95: HO/CL crack (ULSD - WTI) | D95: LEGGED | E95: 1 | F95: HOV6 x42 / CLV6, 1:1 by design (crack, not a fitted beta) | G95: 1000 | H95: 2 | I95: 0.01 | J95: 2 | K95: Oct26 HO-CL Crack
A96: SPREAD_3 | B96: TRUE | C96: 3:2:1 crack (2RB+1HO-3CL)/3 | D96: LEGGED | E96: 1 | F96: RBV6/HOV6/CLV6, structural 3:2:1 - not a fitted beta | G96: 3000 | H96: 6 | I96: 0.01 | J96: 2 | K96: (none listed)
A97: SPREAD_4 | B97: TRUE | C97: CL Oct26-Dec26 Calendar | D97: LISTED | E97: 1 | F97: Single listed calendar spread - beta not applicable | G97: 1000 | H97: 2 | I97: 0.01 | J97: 2 | K97: n/a - this IS the listed spread
A99: HEDGE RATIO BELONGS TO THE PAIR. If the instruments change, beta must be re-derived - a stale beta silently redefines the series. Column F stamps what each beta was computed for.
A100: Contracts charged: BZ-CL and the listed spread are 2 contracts per lot (one per leg); the 3:2:1 crack is 6 (2 RB + 1 HO + 3 CL).
A101: USD per 1.00 of spread: NYMEX energy contracts are 1,000 bbl, so one cent of differential is $10 per leg per lot, i.e. $1,000 per 1.00.
A103: NOTIONAL_BASIS - read this before changing it:
A104: A spread is not an outright, so 'notional' has no single meaning. At 1 lot with CL near $60 and BZ-CL near $7.20: SPREAD_VALUE ~ $7,200, ONE_LEG ~ $60,000, BOTH_LEGS ~ $127,000.
A105: 1% of those is $72, $600 and $1,270. If sigma on this spread turns out to be ~5 cents ($50), only the first is reachable - the others need the spread to travel 12 or 25 sigma, which it will not do. Watch the TP-in-sigma cell on the Dashboard: above about 1 sigma it turns amber.

Sheet Feed
A1: FEED - hidden. Every RTD() formula lives here.
A2: Market | B2: =Dashboard!$C$4
A3: Never put an RTD() formula on Dashboard: a cell holding one repaints whenever the feed moves, and that cannot be prevented while the formula is in the cell.
A5: INSTRUMENTS | B5: Instrument ID | C5: Bid | D5: Ask | E5: High | F5: Low | G5: Mid | H5: Width
A6: =Config!$B$82 | B6: =RTD("tt.rtd",,"Inst",$B$2,$A6) | C6: =IFERROR(IF(OR($B6="",LEFT($B6,4)="Not_"),"",VALUE(RTD("tt.rtd",,$B6,"Bid"))),"") | D6: =IFERROR(IF(OR($B6="",LEFT($B6,4)="Not_"),"",VALUE(RTD("tt.rtd",,$B6,"Ask"))),"") | E6: =IFERROR(IF(OR($B6="",LEFT($B6,4)="Not_"),"",VALUE(RTD("tt.rtd",,$B6,"High"))),"") | F6: =IFERROR(IF(OR($B6="",LEFT($B6,4)="Not_"),"",VALUE(RTD("tt.rtd",,$B6,"Low"))),"") | G6: =IF(OR($C6="",$D6=""),"",($C6+$D6)/2) | H6: =IF(OR($C6="",$D6=""),"",$D6-$C6) | I6: RBOB Gasoline Oct26
A7: =Config!$B$83 | B7: =RTD("tt.rtd",,"Inst",$B$2,$A7) | C7: =IFERROR(IF(OR($B7="",LEFT($B7,4)="Not_"),"",VALUE(RTD("tt.rtd",,$B7,"Bid"))),"") | D7: =IFERROR(IF(OR($B7="",LEFT($B7,4)="Not_"),"",VALUE(RTD("tt.rtd",,$B7,"Ask"))),"") | E7: =IFERROR(IF(OR($B7="",LEFT($B7,4)="Not_"),"",VALUE(RTD("tt.rtd",,$B7,"High"))),"") | F7: =IFERROR(IF(OR($B7="",LEFT($B7,4)="Not_"),"",VALUE(RTD("tt.rtd",,$B7,"Low"))),"") | G7: =IF(OR($C7="",$D7=""),"",($C7+$D7)/2) | H7: =IF(OR($C7="",$D7=""),"",$D7-$C7) | I7: NY Harbor ULSD Oct26
A8: =Config!$B$84 | B8: =RTD("tt.rtd",,"Inst",$B$2,$A8) | C8: =IFERROR(IF(OR($B8="",LEFT($B8,4)="Not_"),"",VALUE(RTD("tt.rtd",,$B8,"Bid"))),"") | D8: =IFERROR(IF(OR($B8="",LEFT($B8,4)="Not_"),"",VALUE(RTD("tt.rtd",,$B8,"Ask"))),"") | E8: =IFERROR(IF(OR($B8="",LEFT($B8,4)="Not_"),"",VALUE(RTD("tt.rtd",,$B8,"High"))),"") | F8: =IFERROR(IF(OR($B8="",LEFT($B8,4)="Not_"),"",VALUE(RTD("tt.rtd",,$B8,"Low"))),"") | G8: =IF(OR($C8="",$D8=""),"",($C8+$D8)/2) | H8: =IF(OR($C8="",$D8=""),"",$D8-$C8) | I8: WTI Crude Oct26
A9: =Config!$B$85 | B9: =RTD("tt.rtd",,"Inst",$B$2,$A9) | C9: =IFERROR(IF(OR($B9="",LEFT($B9,4)="Not_"),"",VALUE(RTD("tt.rtd",,$B9,"Bid"))),"") | D9: =IFERROR(IF(OR($B9="",LEFT($B9,4)="Not_"),"",VALUE(RTD("tt.rtd",,$B9,"Ask"))),"") | E9: =IFERROR(IF(OR($B9="",LEFT($B9,4)="Not_"),"",VALUE(RTD("tt.rtd",,$B9,"High"))),"") | F9: =IFERROR(IF(OR($B9="",LEFT($B9,4)="Not_"),"",VALUE(RTD("tt.rtd",,$B9,"Low"))),"") | G9: =IF(OR($C9="",$D9=""),"",($C9+$D9)/2) | H9: =IF(OR($C9="",$D9=""),"",$D9-$C9) | I9: Brent Last Day Financial Oct26
A10: =Config!$B$86 | B10: =RTD("tt.rtd",,"Inst",$B$2,$A10) | C10: =IFERROR(IF(OR($B10="",LEFT($B10,4)="Not_"),"",VALUE(RTD("tt.rtd",,$B10,"Bid"))),"") | D10: =IFERROR(IF(OR($B10="",LEFT($B10,4)="Not_"),"",VALUE(RTD("tt.rtd",,$B10,"Ask"))),"") | E10: =IFERROR(IF(OR($B10="",LEFT($B10,4)="Not_"),"",VALUE(RTD("tt.rtd",,$B10,"High"))),"") | F10: =IFERROR(IF(OR($B10="",LEFT($B10,4)="Not_"),"",VALUE(RTD("tt.rtd",,$B10,"Low"))),"") | G10: =IF(OR($C10="",$D10=""),"",($C10+$D10)/2) | H10: =IF(OR($C10="",$D10=""),"",$D10-$C10) | I10: Exchange-listed inter-product spread
A11: =Config!$B$87 | B11: =RTD("tt.rtd",,"Inst",$B$2,$A11) | C11: =IFERROR(IF(OR($B11="",LEFT($B11,4)="Not_"),"",VALUE(RTD("tt.rtd",,$B11,"Bid"))),"") | D11: =IFERROR(IF(OR($B11="",LEFT($B11,4)="Not_"),"",VALUE(RTD("tt.rtd",,$B11,"Ask"))),"") | E11: =IFERROR(IF(OR($B11="",LEFT($B11,4)="Not_"),"",VALUE(RTD("tt.rtd",,$B11,"High"))),"") | F11: =IFERROR(IF(OR($B11="",LEFT($B11,4)="Not_"),"",VALUE(RTD("tt.rtd",,$B11,"Low"))),"") | G11: =IF(OR($C11="",$D11=""),"",($C11+$D11)/2) | H11: =IF(OR($C11="",$D11=""),"",$D11-$C11) | I11: Exchange-listed crack spread
A12: =Config!$B$88 | B12: =RTD("tt.rtd",,"Inst",$B$2,$A12) | C12: =IFERROR(IF(OR($B12="",LEFT($B12,4)="Not_"),"",VALUE(RTD("tt.rtd",,$B12,"Bid"))),"") | D12: =IFERROR(IF(OR($B12="",LEFT($B12,4)="Not_"),"",VALUE(RTD("tt.rtd",,$B12,"Ask"))),"") | E12: =IFERROR(IF(OR($B12="",LEFT($B12,4)="Not_"),"",VALUE(RTD("tt.rtd",,$B12,"High"))),"") | F12: =IFERROR(IF(OR($B12="",LEFT($B12,4)="Not_"),"",VALUE(RTD("tt.rtd",,$B12,"Low"))),"") | G12: =IF(OR($C12="",$D12=""),"",($C12+$D12)/2) | H12: =IF(OR($C12="",$D12=""),"",$D12-$C12) | I12: Exchange-listed calendar spread - slot 4
A15: DERIVED & LISTED SPREADS (display) | B15: Basis | C15: Bid | D15: Ask | E15: Mid | F15: Width
A16: BZ - CL | B16: legged | C16: =IF(OR($C$9="",$D$8=""),"",$C$9-$D$8) | D16: =IF(OR($D$9="",$C$8=""),"",$D$9-$C$8) | E16: =IF(OR($G$9="",$G$8=""),"",$G$9-$G$8) | F16: =IF(OR($C16="",$D16=""),"",$D16-$C16)
A17: HO/CL crack | B17: legged | C17: =IF(OR($C$7="",$D$8=""),"",$C$7*42-$D$8) | D17: =IF(OR($D$7="",$C$8=""),"",$D$7*42-$C$8) | E17: =IF(OR($G$7="",$G$8=""),"",$G$7*42-$G$8) | F17: =IF(OR($C17="",$D17=""),"",$D17-$C17)
A18: 3:2:1 crack | B18: legged | C18: =IF(OR($C$6="",$C$7="",$D$8=""),"",(($C$6*2*42)+($C$7*1*42)-($D$8*3))/3) | D18: =IF(OR($D$6="",$D$7="",$C$8=""),"",(($D$6*2*42)+($D$7*1*42)-($C$8*3))/3) | E18: =IF(OR($G$6="",$G$7="",$G$8=""),"",(($G$6*2*42)+($G$7*1*42)-($G$8*3))/3) | F18: =IF(OR($C18="",$D18=""),"",$D18-$C18)
A19: CL Oct26 - BZ Oct26 Inter-Product | B19: listed | C19: =$C$10 | D19: =$D$10 | E19: =$G$10 | F19: =IF(OR($C19="",$D19=""),"",$D19-$C19)
A20: Oct26 HO-CL Crack | B20: listed | C20: =$C$11 | D20: =$D$11 | E20: =$G$11 | F20: =IF(OR($C20="",$D20=""),"",$D20-$C20)
A23: MONITOR LEGS | B23: Edit these formulas to redefine what a monitored spread is made of. spread = LegB - HEDGE_RATIO x LegA, and nothing else - no carry, no fair-value term.
A24: Slot | B24: Side | C24: Composition | D24: Bid | E24: Ask | F24: Mid
A25: 1 | B25: LegA | C25: CLV6 | D25: =$C$8 | E25: =$D$8 | F25: =$G$8
A26: 1 | B26: LegB | C26: BZV6 | D26: =$C$9 | E26: =$D$9 | F26: =$G$9
A27: 2 | B27: LegA | C27: CLV6 | D27: =$C$8 | E27: =$D$8 | F27: =$G$8
A28: 2 | B28: LegB | C28: HOV6 x 42 | D28: =IF($C$7="","",$C$7*42) | E28: =IF($D$7="","",$D$7*42) | F28: =IF($G$7="","",$G$7*42)
A29: 3 | B29: LegA | C29: CLV6 | D29: =$C$8 | E29: =$D$8 | F29: =$G$8
A30: 3 | B30: LegB | C30: (2 x RBV6 + 1 x HOV6) x 42 / 3 | D30: =IF(OR($C$6="",$C$7=""),"",($C$6*2*42+$C$7*1*42)/3) | E30: =IF(OR($D$6="",$D$7=""),"",($D$6*2*42+$D$7*1*42)/3) | F30: =IF(OR($G$6="",$G$7=""),"",($G$6*2*42+$G$7*1*42)/3)
A31: 4 | B31: LegA | C31: (none - LISTED spread)
A32: 4 | B32: LegB | C32: CL Oct26-Dec26 Calendar | D32: =$C$12 | E32: =$D$12 | F32: =$G$12
A34: LISTED-EQUIVALENT ROW PER SLOT (for the side-by-side crossing-cost comparison)
A35: Slot | B35: Feed derived row | C35: Name
A36: 1 | B36: 19 | C36: CL Oct26 - BZ Oct26 Inter-Product
A37: 2 | B37: 20 | C37: Oct26 HO-CL Crack
A38: 3 | C38: (none)
A39: 4 | C39: (none)
A41: Crossing convention used throughout: spread bid = LegB bid - beta x LegA ask ; spread ask = LegB ask - beta x LegA bid ; spread mid = LegB mid - beta x LegA mid.
A42: For a LISTED slot LegA is empty and is treated as zero, so the listed quote passes straight through untouched.

Sheet Buffer
A1: BUFFER - hidden. Flushed circular buffers (crash / restart recovery). | M1: Written by VBA every FLUSH_SEC seconds, so a crash loses at most a minute.
M2: On open, WarmStart reloads a slot only if its stamped LOOKBACK_MIN, HEDGE_RATIO and leg labels still match Config, and the newest sample is younger than WARM_START_MAX_AGE_MIN.
A3: SLOT 1 | D3: SLOT 2 | G3: SLOT 3 | J3: SLOT 4 | M3: Elapsed collection is credited from the OLDEST recovered sample - otherwise every restart costs another two hours before a usable z.
A4: Name | D4: Name | G4: Name | J4: Name | M4: Seeding drops CONSECUTIVE identical values only. A spread genuinely revisiting a level is a real observation, not a duplicate.
A5: Legs | D5: Legs | G5: Legs | J5: Legs
A6: HEDGE_RATIO | D6: HEDGE_RATIO | G6: HEDGE_RATIO | J6: HEDGE_RATIO
A7: LOOKBACK_MIN | D7: LOOKBACK_MIN | G7: LOOKBACK_MIN | J7: LOOKBACK_MIN
A8: Count / last flush | D8: Count / last flush | G8: Count / last flush | J8: Count / last flush
A9: Time (serial) | B9: Spread value | D9: Time (serial) | E9: Spread value | G9: Time (serial) | H9: Spread value | J9: Time (serial) | K9: Spread value

Sheet Log
A1: LOG - timestamped signal events
A2: One line when a state STARTS and one when it CLEARS - never one per poll. Reviewable after the session.
A3: Time | B3: Spread | C3: Event | D3: z | E3: Mean | F3: Sigma | G3: Spread | H3: Bid | I3: Ask | J3: Signal | K3: Edge | L3: Note

Sheet Setup
B1: SETUP - turning this .xlsx into the working .xlsm
B3: openpyxl cannot author VBA, so this file ships as an .xlsx carrying all structure and formatting, plus a .bas module to import. Six steps, once.
B4: 1. Open TT_ZScore_Monitor.xlsx in Excel on the machine running TT and the TT RTD server.
B5: 2. File > Save As > Excel Macro-Enabled Workbook (.xlsm). Keep the same folder.
B6: 3. Alt+F11 to open the VBA editor. File > Import File... and choose TTZMonitor.bas.
B7: 4. In the editor, double-click ThisWorkbook, clear the pane with Ctrl+A then Delete, and paste the contents of ThisWorkbook.txt verbatim. Do NOT copy it out of TTZMonitor.bas - the copy there is inside a comment block, and pasting it with the apostrophes attached gives 'Compile error: Expected End Sub'.
B8: 5. Back on Dashboard, insert two shapes over cells N2 and P2 (Insert > Shapes > Rectangle), right-click each > Assign Macro > StartMonitor and StopMonitor. Until you do, run them from Alt+F8.
B9: 6. Save. Click START. The Feed sheet stays hidden; you never need to look at it.
B10: Step 4 is NOT optional here. The capture timer is a Windows user32 timer, and one that outlives the workbook keeps firing into a module that no longer has its sheets - which crashes Excel. Workbook_BeforeClose calls StopMonitor and kills it.
B12: WHAT TO CHECK ON THE FIRST RUN
B13: - Feed sheet column B (instrument ids) fills in. If it stays blank, the TT short name in Feed column A does not match TT, or the market in Dashboard!C4 is wrong.
B14: - Dashboard prices move, but the sheet does NOT flash. If it flashes, something volatile has been reintroduced - search the workbook for NOW, TODAY, OFFSET, INDIRECT, RAND.
... B21: Live off Config. Edit the two assumed market widths below; everything else follows.
B22: Assumed width, each outright leg (spread units) | C22: 0.02 | E22: Assumed width, listed spread (spread units) | F22: 0.02
B24: At LOTS from Config, per leg | C24: Total cost | D24: min sigma @ z = 3.0 | E24: min sigma @ z = 2.5 | F24: min sigma @ live ENTRY_Z
B25: Legging the outrights | C25: =2*Config!$B$74*Config!$B$41+(2*$C$22)*1000*Config!$B$41 | D25: =Config!$B$47*$C$25/(0.5*3*1000*Config!$B$41) | E25: =Config!$B$47*$C$25/(0.5*2.5*1000*Config!$B$41) | F25: =Config!$B$47*$C$25/(0.5*Config!$B$34*1000*Config!$B$41)
B26: Listed inter-product spread | C26: =2*Config!$B$74*Config!$B$41+$F$22*1000*Config!$B$41 | D26: =Config!$B$47*$C$26/(0.5*3*1000*Config!$B$41) | E26: =Config!$B$47*$C$26/(0.5*2.5*1000*Config!$B$41) | F26: =Config!$B$47*$C$26/(0.5*Config!$B$34*1000*Config!$B$41)
B28: capture = 0.5 x |z| x sigma x USD-per-point x LOTS. An entry passes when capture >= EDGE_MULTIPLE x total cost.
B29: A lower ENTRY_Z means less expected capture per entry, so it RAISES the sigma the spread must have. 2.5 instead of 3.0 raises it by about 20%.
B31: ASSUMPTIONS MADE WHILE BUILDING THIS - CHECK THEM
B32: - The repository was empty, so the existing Dashboard layout was reconstructed from the cell references given in the spec (C4, B6, C7, H7/H8, P7/P8, H12/H13/H14/I14, L3). Those coordinates are honoured exactly; the surrounding rows are a best reconstruction. Compare against your live sheet before relying on it.
B33: - The 3:2:1 ask row now mirrors the bid row: I15 uses H14 (CL BID), not I14. The bid row is unchanged. This is the convention the spec described; confirm it is the one you want.
B34: - COMMISSION_BASIS defaults to CONSERVATIVE ($3.82 per lot per leg round turn, reading CME's $1.50 as per side). Switch it to CME_PER_RT on Config if the rate card proves otherwise.
B35: - Contracts charged commission: 2 for BZ-CL and the listed spread, 6 for the 3:2:1 crack (2 RB + 1 HO + 3 CL). Change it in the Config spread table if your clearing differs.
B36: - Slot 3 (3:2:1) has no exchange-listed equivalent, so its LISTED crossing-cost column reads n/a.
B37: - MIN_SIGMA ships at 0 because sigma on these spreads has never been measured. Set it once you have a session of data - until then the degenerate-window guard rests on MAX_ABS_Z alone.
B38: - Application.OnTime cannot go below about one second, so capture at 100 ms runs on a user32 SetTimer with an OnTime watchdog that re-arms it (Excel silently kills API timers when a modal dialog opens). If SetTimer is unavailable, CAPTURE_MS is clamped to 1000 and everything still works - only alert latency changes, not the statistics.
B39: - Capturing at 100 ms does not mean storing at 100 ms, and after dedupe it does not change sigma either. The window holds quote CHANGES, not poll ticks; subsampling a mean-reverting level series is unbiased. 100 ms buys latency to the chime, which for manual execution is not measurable in human terms - so the real reason to capture fast is simply that no genuine quote change is missed.
